lxml_xpath_ipaddress/__init__.py
lxml_xpath_ipaddress/func_namespace.py
lxml_xpath_ipaddress/in_subnet.py
lxml_xpath_ipaddress/ip4.py
lxml_xpath_ipaddress/ip4or6.py
lxml_xpath_ipaddress/ip6.py
lxml_xpath_ipaddress-0.2.0.dist-info/LICENSE
lxml_xpath_ipaddress-0.2.0.dist-info/METADATA
lxml_xpath_ipaddress-0.2.0.dist-info/WHEEL
lxml_xpath_ipaddress-0.2.0.dist-info/top_level.txt
lxml_xpath_ipaddress-0.2.0.dist-info/RECORD
