Metadata-Version: 2.1
Name: lxml-xpath-ipaddress
Version: 0.2.0
Summary: LXML xpath extension library for ipaddress
Home-page: https://github.com/jeremyschulman/junospyez-ossh-server
Author: jschulman@juniper.net
License: UNKNOWN
Platform: UNKNOWN
Classifier: Programming Language :: Python :: 3
Classifier: License :: OSI Approved :: MIT License
Classifier: Operating System :: OS Independent
